<?xml version="1.0" encoding="utf-8" ?>
<dwsync>
<file name="el-hotel-pacha-4-estrellas.jpg" server="176.28.103.205//webspace/httpdocs/hotelibizabarato.com/" local="131291669938663122" remote="131295568800000000" Dst="1" />
<file name="el-hotel-pacha-ibiza-ciudad.jpg" server="176.28.103.205//webspace/httpdocs/hotelibizabarato.com/" local="131291669936588209" remote="131295568800000000" Dst="1" />
<file name="el-hotel-pacha-ibiza.jpg" server="176.28.103.205//webspace/httpdocs/hotelibizabarato.com/" local="131291669935142679" remote="131295568800000000" Dst="1" />
<file name="el-hotel-pacha-mas-baratos.jpg" server="176.28.103.205//webspace/httpdocs/hotelibizabarato.com/" local="131291669930437624" remote="131295568800000000" Dst="1" />
<file name="el-hotel-pacha-mas-ofertas.jpg" server="176.28.103.205//webspace/httpdocs/hotelibizabarato.com/" local="131291669928406927" remote="131295568800000000" Dst="1" />
<file name="el-hotel-pacha-mas-barato.jpg" server="176.28.103.205//webspace/httpdocs/hotelibizabarato.com/" local="131291669933447645" remote="131295568800000000" Dst="1" />
<file name="el-hotel-pacha-mejor-book.jpg" server="176.28.103.205//webspace/httpdocs/hotelibizabarato.com/" local="131291669926916657" remote="131295568800000000" Dst="1" />
<file name="el-hotel-pacha-mejor-consejo.jpg" server="176.28.103.205//webspace/httpdocs/hotelibizabarato.com/" local="131291669922046063" remote="131295568800000000" Dst="1" />
<file name="el-hotel-pacha-mejor-booking.jpg" server="176.28.103.205//webspace/httpdocs/hotelibizabarato.com/" local="131291669924256319" remote="131295568800000000" Dst="1" />
<file name="el-hotel-pacha-mejor-hotel.jpg" server="176.28.103.205//webspace/httpdocs/hotelibizabarato.com/" local="131291669918382685" remote="131295568800000000" Dst="1" />
<file name="el-hotel-pacha-mejor-habitacion.jpg" server="176.28.103.205//webspace/httpdocs/hotelibizabarato.com/" local="131291669921405949" remote="131295568800000000" Dst="1" />
<file name="el-hotel-pacha-mejor-oferta.jpg" server="176.28.103.205//webspace/httpdocs/hotelibizabarato.com/" local="131291669915651859" remote="131295568800000000" Dst="1" />
<file name="el-hotel-pacha-mejor-reserva.jpg" server="176.28.103.205//webspace/httpdocs/hotelibizabarato.com/" local="131291669911481325" remote="131295568800000000" Dst="1" />
<file name="el-hotel-pacha-mejor-precio.jpg" server="176.28.103.205//webspace/httpdocs/hotelibizabarato.com/" local="131291669914391698" remote="131295568800000000" Dst="1" />
<file name="el-hotel-pacha-mejores-habitaciones.jpg" server="176.28.103.205//webspace/httpdocs/hotelibizabarato.com/" local="131291669907636118" remote="131295568800000000" Dst="1" />
<file name="el-hotel-pacha-mejores-consejos.jpg" server="176.28.103.205//webspace/httpdocs/hotelibizabarato.com/" local="131291669909186567" remote="131295568800000000" Dst="1" />
<file name="el-hotel-pacha-mejores-opiniones.jpg" server="176.28.103.205//webspace/httpdocs/hotelibizabarato.com/" local="131291669905201043" remote="131295568800000000" Dst="1" />
<file name="el-hotel-pacha-mejores-reservas.jpg" server="176.28.103.205//webspace/httpdocs/hotelibizabarato.com/" local="131291669903340790" remote="131295568800000000" Dst="1" />
<file name="el-hotel-pacha.jpg" server="176.28.103.205//webspace/httpdocs/hotelibizabarato.com/" local="131291669900795010" remote="131295568800000000" Dst="1" />
</dwsync>